task_timer_birdhouses/__init__.py
task_timer_birdhouses/task_timer.py
task_timer_birdhouses-1.0.1.dist-info/METADATA
task_timer_birdhouses-1.0.1.dist-info/WHEEL
task_timer_birdhouses-1.0.1.dist-info/licenses/LICENSE
task_timer_birdhouses-1.0.1.dist-info/RECORD
