Metadata-Version: 2.1
Name: task_timer_birdhouses
Version: 1.0.1
Summary: You can use `TaskTimer` to automatically calculate and execute when a given function will be executed based on a specified duration in seconds.
Project-URL: Homepage, https://github.com/birdhouses/TaskTimer
Project-URL: Bug Tracker, https://github.com/birdhouses/TaskTimer/issues
Author-email: birdhouses <peerdenhoed@hotmail.nl>
License-File: LICENSE
Classifier: License :: OSI Approved :: MIT License
Classifier: Operating System :: OS Independent
Classifier: Programming Language :: Python :: 3
Requires-Python: >=3.7
